neads/__init__.py
neads/logging_autoconfig.py
neads/_internal_utils/__init__.py
neads/_internal_utils/graph_utils.py
neads/_internal_utils/memory_info.py
neads/_internal_utils/object_temp_file.py
neads/_internal_utils/plain_graph_wrappers.py
neads/_internal_utils/serializers/__init__.py
neads/_internal_utils/serializers/i_iserializer.py
neads/_internal_utils/serializers/pickle_serializer.py
neads/activation_model/__init__.py
neads/activation_model/activation_graph.py
neads/activation_model/data_definition.py
neads/activation_model/plugin.py
neads/activation_model/symbolic_argument_set.py
neads/activation_model/symbolic_objects/__init__.py
neads/activation_model/symbolic_objects/composite_object.py
neads/activation_model/symbolic_objects/symbolic_object.py
neads/activation_model/symbolic_objects/symbolic_object_exception.py
neads/activation_model/symbolic_objects/value.py
neads/activation_model/symbolic_objects/concrete_composite_objects/__init__.py
neads/activation_model/symbolic_objects/concrete_composite_objects/dict_object.py
neads/activation_model/symbolic_objects/concrete_composite_objects/list_object.py
neads/database/__init__.py
neads/database/file_database.py
neads/database/i_database.py
neads/evaluation_manager/__init__.py
neads/evaluation_manager/i_evaluation_manager.py
neads/evaluation_manager/single_thread_evaluation_manager/__init__.py
neads/evaluation_manager/single_thread_evaluation_manager/data_node.py
neads/evaluation_manager/single_thread_evaluation_manager/eligibility_detector.py
neads/evaluation_manager/single_thread_evaluation_manager/evaluation_manager.py
neads/evaluation_manager/single_thread_evaluation_manager/evaluation_state.py
neads/evaluation_manager/single_thread_evaluation_manager/evaluation_algorithms/__init__.py
neads/evaluation_manager/single_thread_evaluation_manager/evaluation_algorithms/complex_algorithm.py
neads/evaluation_manager/single_thread_evaluation_manager/evaluation_algorithms/i_evaluation_algorithm.py
neads-1.0.2.dist-info/METADATA
neads-1.0.2.dist-info/WHEEL
neads-1.0.2.dist-info/top_level.txt
neads-1.0.2.dist-info/RECORD
